{"statusCode":"200","statusText":"OK","errors":[],"callback":[{"funcName":"toggleKerngebietAuswahl","funcArgs":{"show":true,"text":"<p class=\"boxtxt\">Flex-System: Bitte benutzen Sie die Suche, um den n\u00e4chsten Standort zu finden!<\/p>"}},{"funcName":"showKerngebiet","funcArgs":{"stadtId":"90","zoomIn":true}},{"funcName":"jQuery('#stadt_id').val","funcArgs":"90"}],"icons":{"bikeicon":{"iconName":"bikeicon","iconData":{"url":"\/resourcen\/map_icons\/500\/fahrrad.png","width":31,"height":40,"originWidth":0,"originHeight":0,"anchorWidth":16,"anchorHeight":40},"shadowData":{"url":"\/resourcen\/map_icons\/500\/fahrrad_shadow.png","width":52,"height":40,"originWidth":0,"originHeight":0,"anchorWidth":16,"anchorHeight":40}}},"cities":[],"marker":[{"lat":"48.150135000000000","lng":"11.555741000000000","iconName":"bikeicon","iconNameSelected":"","hal2option":{"minZoom":"11","maxZoom":false,"tooltip":"'Bike-Standort'","id":"23588354948471","openinfo":"openDynamicInfoWindow","click":"openDynamicInfoWindow","mouseover":"showToolTip","mouseout":"hideToolTip","dblclick":false,"rclick":false,"draggable":false,"proc":"bikesuche","cabfixflex":"flex","firmen":"500,510,530,540","objectname":"bikemarker","meta_id":"","standort_id":"","bikes":"1030","bikelist":[{"Number":"1030","Version":"5","canBeRented":true,"canBeReturned":false,"MarkeID":"1312","MarkeName":"CallBike","isPedelec":false,"FirmaID":"500"}],"objecttyp":"cab_standort","clustername":"bikecluster","filter":["cab_flex"]}},{"lat":"48.147884000000000","lng":"11.556335000000000","iconName":"bikeicon","iconNameSelected":"","hal2option":{"minZoom":"11","maxZoom":false,"tooltip":"'Nymphenburger&nbsp;Str.&nbsp;\/&nbsp;Sandstr.'","id":"2358840980323","openinfo":"openDynamicInfoWindow","click":"openDynamicInfoWindow","mouseover":"showToolTip","mouseout":"hideToolTip","dblclick":false,"rclick":false,"draggable":false,"proc":"bikesuche","cabfixflex":"flex","firmen":"500,510,530,540","objectname":"bikemarker","meta_id":"","standort_id":"22750","bikes":"1034","bikelist":[{"Number":"1034","Version":"5","canBeRented":true,"canBeReturned":false,"MarkeID":"1312","MarkeName":"CallBike","isPedelec":false,"FirmaID":"500"}],"objecttyp":"cab_standort","clustername":"bikecluster","filter":["cab_flex"]}},{"lat":"48.149166670000000","lng":"11.550000000000000","iconName":"bikeicon","iconNameSelected":"","hal2option":{"minZoom":"11","maxZoom":false,"tooltip":"'Loristr.&nbsp;\/&nbsp;Nymphenburger&nbsp;Str.'","id":"23582257632349","openinfo":"openDynamicInfoWindow","click":"openDynamicInfoWindow","mouseover":"showToolTip","mouseout":"hideToolTip","dblclick":false,"rclick":false,"draggable":false,"proc":"bikesuche","cabfixflex":"flex","firmen":"500,510,530,540","objectname":"bikemarker","meta_id":"","standort_id":"14134","bikes":"0173","bikelist":[{"Number":"0173","Version":"5","canBeRented":true,"canBeReturned":false,"MarkeID":"1312","MarkeName":"CallBike","isPedelec":false,"FirmaID":"500"}],"objecttyp":"cab_standort","clustername":"bikecluster","filter":["cab_flex"]}},{"lat":"48.151882000000000","lng":"11.554756000000000","iconName":"bikeicon","iconNameSelected":"","hal2option":{"minZoom":"11","maxZoom":false,"tooltip":"'Erzgie\u00dfereistr.&nbsp;\/&nbsp;Kreittmayrstr.'","id":"23587777501299","openinfo":"openDynamicInfoWindow","click":"openDynamicInfoWindow","mouseover":"showToolTip","mouseout":"hideToolTip","dblclick":false,"rclick":false,"draggable":false,"proc":"bikesuche","cabfixflex":"flex","firmen":"500,510,530,540","objectname":"bikemarker","meta_id":"","standort_id":"22745","bikes":"6962","bikelist":[{"Number":"6962","Version":"5","canBeRented":true,"canBeReturned":false,"MarkeID":"1312","MarkeName":"CallBike","isPedelec":false,"FirmaID":"500"}],"objecttyp":"cab_standort","clustername":"bikecluster","filter":["cab_flex"]}},{"lat":"48.149006000000000","lng":"11.549030000000000","iconName":"bikeicon","iconNameSelected":"","hal2option":{"minZoom":"11","maxZoom":false,"tooltip":"'Adamstr.&nbsp;\/&nbsp;Nymphenburger&nbsp;Str.'","id":"23581228016458","openinfo":"openDynamicInfoWindow","click":"openDynamicInfoWindow","mouseover":"showToolTip","mouseout":"hideToolTip","dblclick":false,"rclick":false,"draggable":false,"proc":"bikesuche","cabfixflex":"flex","firmen":"500,510,530,540","objectname":"bikemarker","meta_id":"","standort_id":"9102","bikes":"6847","bikelist":[{"Number":"6847","Version":"5","canBeRented":true,"canBeReturned":false,"MarkeID":"1312","MarkeName":"CallBike","isPedelec":false,"FirmaID":"500"}],"objecttyp":"cab_standort","clustername":"bikecluster","filter":["cab_flex"]}},{"lat":"48.149002000000000","lng":"11.548909000000000","iconName":"bikeicon","iconNameSelected":"","hal2option":{"minZoom":"11","maxZoom":false,"tooltip":"'Adamstr.&nbsp;\/&nbsp;Nymphenburger&nbsp;Str.'","id":"23581103505536","openinfo":"openDynamicInfoWindow","click":"openDynamicInfoWindow","mouseover":"showToolTip","mouseout":"hideToolTip","dblclick":false,"rclick":false,"draggable":false,"proc":"bikesuche","cabfixflex":"flex","firmen":"500,510,530,540","objectname":"bikemarker","meta_id":"","standort_id":"9102","bikes":"0013","bikelist":[{"Number":"0013","Version":"5","canBeRented":true,"canBeReturned":false,"MarkeID":"1312","MarkeName":"CallBike","isPedelec":false,"FirmaID":"500"}],"objecttyp":"cab_standort","clustername":"bikecluster","filter":["cab_flex"]}},{"lat":"48.152640000000000","lng":"11.553412000000000","iconName":"bikeicon","iconNameSelected":"","hal2option":{"minZoom":"11","maxZoom":false,"tooltip":"'Ferdinand-Miller-Platz&nbsp;\/&nbsp;Loristr.'","id":"23586591292675","openinfo":"openDynamicInfoWindow","click":"openDynamicInfoWindow","mouseover":"showToolTip","mouseout":"hideToolTip","dblclick":false,"rclick":false,"draggable":false,"proc":"bikesuche","cabfixflex":"flex","firmen":"500,510,530,540","objectname":"bikemarker","meta_id":"","standort_id":"14367","bikes":"6540","bikelist":[{"Number":"6540","Version":"5","canBeRented":true,"canBeReturned":false,"MarkeID":"1312","MarkeName":"CallBike","isPedelec":false,"FirmaID":"500"}],"objecttyp":"cab_standort","clustername":"bikecluster","filter":["cab_flex"]}},{"lat":"48.145690000000000","lng":"11.551425000000000","iconName":"bikeicon","iconNameSelected":"","hal2option":{"minZoom":"11","maxZoom":false,"tooltip":"'Marsstr.&nbsp;\/&nbsp;Spatenstr.'","id":"23582860876243","openinfo":"openDynamicInfoWindow","click":"openDynamicInfoWindow","mouseover":"showToolTip","mouseout":"hideToolTip","dblclick":false,"rclick":false,"draggable":false,"proc":"bikesuche","cabfixflex":"flex","firmen":"500,510,530,540","objectname":"bikemarker","meta_id":"","standort_id":"16300","bikes":"1513","bikelist":[{"Number":"1513","Version":"5","canBeRented":true,"canBeReturned":false,"MarkeID":"1312","MarkeName":"CallBike","isPedelec":false,"FirmaID":"500"}],"objecttyp":"cab_standort","clustername":"bikecluster","filter":["cab_flex"]}},{"lat":"48.152290000000000","lng":"11.551157000000000","iconName":"bikeicon","iconNameSelected":"","hal2option":{"minZoom":"11","maxZoom":false,"tooltip":"'Gaiglstr.&nbsp;\/&nbsp;Lothstr.'","id":"23584203647771","openinfo":"openDynamicInfoWindow","click":"openDynamicInfoWindow","mouseover":"showToolTip","mouseout":"hideToolTip","dblclick":false,"rclick":false,"draggable":false,"proc":"bikesuche","cabfixflex":"flex","firmen":"500,510,530,540","objectname":"bikemarker","meta_id":"","standort_id":"49269","bikes":"5191","bikelist":[{"Number":"5191","Version":"5","canBeRented":true,"canBeReturned":false,"MarkeID":"1312","MarkeName":"CallBike","isPedelec":false,"FirmaID":"500"}],"objecttyp":"cab_standort","clustername":"bikecluster","filter":["cab_flex"]}},{"lat":"48.151111110000000","lng":"11.548888890000000","iconName":"bikeicon","iconNameSelected":"","hal2option":{"minZoom":"11","maxZoom":false,"tooltip":"'Lothstr.&nbsp;\/&nbsp;Thorwaldsenstr.'","id":"23581599439805","openinfo":"openDynamicInfoWindow","click":"openDynamicInfoWindow","mouseover":"showToolTip","mouseout":"hideToolTip","dblclick":false,"rclick":false,"draggable":false,"proc":"bikesuche","cabfixflex":"flex","firmen":"500,510,530,540","objectname":"bikemarker","meta_id":"","standort_id":"262","bikes":"1313","bikelist":[{"Number":"1313","Version":"5","canBeRented":true,"canBeReturned":false,"MarkeID":"1312","MarkeName":"CallBike","isPedelec":false,"FirmaID":"500"}],"objecttyp":"cab_standort","clustername":"bikecluster","filter":["cab_flex"]}},{"lat":"48.151398000000000","lng":"11.558122000000000","iconName":"bikeicon","iconNameSelected":"","hal2option":{"minZoom":"11","maxZoom":false,"tooltip":"'Dachauer&nbsp;Str.&nbsp;\/&nbsp;Ma\u00dfmannstr.'","id":"23591094348388","openinfo":"openDynamicInfoWindow","click":"openDynamicInfoWindow","mouseover":"showToolTip","mouseout":"hideToolTip","dblclick":false,"rclick":false,"draggable":false,"proc":"bikesuche","cabfixflex":"flex","firmen":"500,510,530,540","objectname":"bikemarker","meta_id":"","standort_id":"8873","bikes":"1226","bikelist":[{"Number":"1226","Version":"5","canBeRented":true,"canBeReturned":false,"MarkeID":"1312","MarkeName":"CallBike","isPedelec":false,"FirmaID":"500"}],"objecttyp":"cab_standort","clustername":"bikecluster","filter":["cab_flex"]}},{"lat":"48.152640000000000","lng":"11.555696000000000","iconName":"bikeicon","iconNameSelected":"","hal2option":{"minZoom":"11","maxZoom":false,"tooltip":"'Dachauer&nbsp;Str.&nbsp;\/&nbsp;Erzgie\u00dfereistr.'","id":"23588922600183","openinfo":"openDynamicInfoWindow","click":"openDynamicInfoWindow","mouseover":"showToolTip","mouseout":"hideToolTip","dblclick":false,"rclick":false,"draggable":false,"proc":"bikesuche","cabfixflex":"flex","firmen":"500,510,530,540","objectname":"bikemarker","meta_id":"","standort_id":"511","bikes":"0806","bikelist":[{"Number":"0806","Version":"5","canBeRented":true,"canBeReturned":false,"MarkeID":"1312","MarkeName":"CallBike","isPedelec":false,"FirmaID":"500"}],"objecttyp":"cab_standort","clustername":"bikecluster","filter":["cab_flex"]}},{"lat":"48.149525000000000","lng":"11.547735000000000","iconName":"bikeicon","iconNameSelected":"","hal2option":{"minZoom":"11","maxZoom":false,"tooltip":"'Lothstr.&nbsp;\/&nbsp;Nymphenburger&nbsp;Str.'","id":"23580032974444","openinfo":"openDynamicInfoWindow","click":"openDynamicInfoWindow","mouseover":"showToolTip","mouseout":"hideToolTip","dblclick":false,"rclick":false,"draggable":false,"proc":"bikesuche","cabfixflex":"flex","firmen":"500,510,530,540","objectname":"bikemarker","meta_id":"","standort_id":"33967","bikes":"0395","bikelist":[{"Number":"0395","Version":"5","canBeRented":true,"canBeReturned":false,"MarkeID":"1312","MarkeName":"CallBike","isPedelec":false,"FirmaID":"500"}],"objecttyp":"cab_standort","clustername":"bikecluster","filter":["cab_flex"]}},{"lat":"48.153010000000000","lng":"11.555680000000000","iconName":"bikeicon","iconNameSelected":"","hal2option":{"minZoom":"11","maxZoom":false,"tooltip":"'Dachauer&nbsp;Str.&nbsp;\/&nbsp;Erzgie\u00dfereistr.'","id":"23588996896791","openinfo":"openDynamicInfoWindow","click":"openDynamicInfoWindow","mouseover":"showToolTip","mouseout":"hideToolTip","dblclick":false,"rclick":false,"draggable":false,"proc":"bikesuche","cabfixflex":"flex","firmen":"500,510,530,540","objectname":"bikemarker","meta_id":"","standort_id":"511","bikes":"0908","bikelist":[{"Number":"0908","Version":"5","canBeRented":true,"canBeReturned":false,"MarkeID":"1312","MarkeName":"CallBike","isPedelec":false,"FirmaID":"500"}],"objecttyp":"cab_standort","clustername":"bikecluster","filter":["cab_flex"]}},{"lat":"48.150590000000000","lng":"11.547029000000000","iconName":"bikeicon","iconNameSelected":"","hal2option":{"minZoom":"11","maxZoom":false,"tooltip":"'Maillingerstr.&nbsp;\/&nbsp;Nymphenburger&nbsp;Str.'","id":"23579572920159","openinfo":"openDynamicInfoWindow","click":"openDynamicInfoWindow","mouseover":"showToolTip","mouseout":"hideToolTip","dblclick":false,"rclick":false,"draggable":false,"proc":"bikesuche","cabfixflex":"flex","firmen":"500,510,530,540","objectname":"bikemarker","meta_id":"","standort_id":"22731","bikes":"6667","bikelist":[{"Number":"6667","Version":"5","canBeRented":true,"canBeReturned":false,"MarkeID":"1312","MarkeName":"CallBike","isPedelec":false,"FirmaID":"500"}],"objecttyp":"cab_standort","clustername":"bikecluster","filter":["cab_flex"]}},{"lat":"48.153503000000000","lng":"11.557010000000000","iconName":"bikeicon","iconNameSelected":"","hal2option":{"minZoom":"11","maxZoom":false,"tooltip":"'Bike-Standort'","id":"2359047510556","openinfo":"openDynamicInfoWindow","click":"openDynamicInfoWindow","mouseover":"showToolTip","mouseout":"hideToolTip","dblclick":false,"rclick":false,"draggable":false,"proc":"bikesuche","cabfixflex":"flex","firmen":"500,510,530,540","objectname":"bikemarker","meta_id":"","standort_id":"","bikes":"1765","bikelist":[{"Number":"1765","Version":"5","canBeRented":true,"canBeReturned":false,"MarkeID":"1312","MarkeName":"CallBike","isPedelec":false,"FirmaID":"500"}],"objecttyp":"cab_standort","clustername":"bikecluster","filter":["cab_flex"]}},{"lat":"48.145725000000000","lng":"11.559776000000000","iconName":"bikeicon","iconNameSelected":"","hal2option":{"minZoom":"11","maxZoom":false,"tooltip":"'Dachauer&nbsp;Str.&nbsp;\/&nbsp;Karlstr.'","id":"23591392420915","openinfo":"openDynamicInfoWindow","click":"openDynamicInfoWindow","mouseover":"showToolTip","mouseout":"hideToolTip","dblclick":false,"rclick":false,"draggable":false,"proc":"bikesuche","cabfixflex":"flex","firmen":"500,510,530,540","objectname":"bikemarker","meta_id":"","standort_id":"8877","bikes":"0664","bikelist":[{"Number":"0664","Version":"5","canBeRented":true,"canBeReturned":false,"MarkeID":"1312","MarkeName":"CallBike","isPedelec":false,"FirmaID":"500"}],"objecttyp":"cab_standort","clustername":"bikecluster","filter":["cab_flex"]}},{"lat":"48.149536000000000","lng":"11.561525000000000","iconName":"bikeicon","iconNameSelected":"","hal2option":{"minZoom":"11","maxZoom":false,"tooltip":"'Bike-Standort'","id":"23594110794908","openinfo":"openDynamicInfoWindow","click":"openDynamicInfoWindow","mouseover":"showToolTip","mouseout":"hideToolTip","dblclick":false,"rclick":false,"draggable":false,"proc":"bikesuche","cabfixflex":"flex","firmen":"500,510,530,540","objectname":"bikemarker","meta_id":"","standort_id":"","bikes":"5886","bikelist":[{"Number":"5886","Version":"5","canBeRented":true,"canBeReturned":false,"MarkeID":"1312","MarkeName":"CallBike","isPedelec":false,"FirmaID":"500"}],"objecttyp":"cab_standort","clustername":"bikecluster","filter":["cab_flex"]}},{"lat":"48.151370000000000","lng":"11.561630000000000","iconName":"bikeicon","iconNameSelected":"","hal2option":{"minZoom":"11","maxZoom":false,"tooltip":"'Schwindstr.&nbsp;\/&nbsp;Theresienstr.'","id":"2359466727744","openinfo":"openDynamicInfoWindow","click":"openDynamicInfoWindow","mouseover":"showToolTip","mouseout":"hideToolTip","dblclick":false,"rclick":false,"draggable":false,"proc":"bikesuche","cabfixflex":"flex","firmen":"500,510,530,540","objectname":"bikemarker","meta_id":"","standort_id":"39994","bikes":"0655","bikelist":[{"Number":"0655","Version":"5","canBeRented":true,"canBeReturned":false,"MarkeID":"1312","MarkeName":"CallBike","isPedelec":false,"FirmaID":"500"}],"objecttyp":"cab_standort","clustername":"bikecluster","filter":["cab_flex"]}},{"lat":"48.149166670000000","lng":"11.562777780000000","iconName":"bikeicon","iconNameSelected":"","hal2option":{"minZoom":"11","maxZoom":false,"tooltip":"'Augustenstr.&nbsp;\/&nbsp;Gabelsbergerstr.'","id":"23595298567668","openinfo":"openDynamicInfoWindow","click":"openDynamicInfoWindow","mouseover":"showToolTip","mouseout":"hideToolTip","dblclick":false,"rclick":false,"draggable":false,"proc":"bikesuche","cabfixflex":"flex","firmen":"500,510,530,540","objectname":"bikemarker","meta_id":"","standort_id":"22766","bikes":"1805","bikelist":[{"Number":"1805","Version":"5","canBeRented":true,"canBeReturned":false,"MarkeID":"1312","MarkeName":"CallBike","isPedelec":false,"FirmaID":"500"}],"objecttyp":"cab_standort","clustername":"bikecluster","filter":["cab_flex"]}},{"lat":"48.143333330000000","lng":"11.550277780000000","iconName":"bikeicon","iconNameSelected":"","hal2option":{"minZoom":"11","maxZoom":false,"tooltip":"'Arnulfstr.&nbsp;\/&nbsp;Zirkus-Krone-Str.'","id":"23581112637376","openinfo":"openDynamicInfoWindow","click":"openDynamicInfoWindow","mouseover":"showToolTip","mouseout":"hideToolTip","dblclick":false,"rclick":false,"draggable":false,"proc":"bikesuche","cabfixflex":"flex","firmen":"500,510,530,540","objectname":"bikemarker","meta_id":"","standort_id":"39980","bikes":"1918","bikelist":[{"Number":"1918","Version":"5","canBeRented":true,"canBeReturned":false,"MarkeID":"1312","MarkeName":"CallBike","isPedelec":false,"FirmaID":"500"}],"objecttyp":"cab_standort","clustername":"bikecluster","filter":["cab_flex"]}},{"lat":"48.149136000000000","lng":"11.562858000000000","iconName":"bikeicon","iconNameSelected":"","hal2option":{"minZoom":"11","maxZoom":false,"tooltip":"'Augustenstr.&nbsp;\/&nbsp;Gabelsbergerstr.'","id":"23595372902132","openinfo":"openDynamicInfoWindow","click":"openDynamicInfoWindow","mouseover":"showToolTip","mouseout":"hideToolTip","dblclick":false,"rclick":false,"draggable":false,"proc":"bikesuche","cabfixflex":"flex","firmen":"500,510,530,540","objectname":"bikemarker","meta_id":"","standort_id":"22766","bikes":"6416","bikelist":[{"Number":"6416","Version":"5","canBeRented":true,"canBeReturned":false,"MarkeID":"1312","MarkeName":"CallBike","isPedelec":false,"FirmaID":"500"}],"objecttyp":"cab_standort","clustername":"bikecluster","filter":["cab_flex"]}},{"lat":"48.153690000000000","lng":"11.559665000000000","iconName":"bikeicon","iconNameSelected":"","hal2option":{"minZoom":"11","maxZoom":false,"tooltip":"'He\u00dfstr.&nbsp;\/&nbsp;Winzererstr.'","id":"23593230489143","openinfo":"openDynamicInfoWindow","click":"openDynamicInfoWindow","mouseover":"showToolTip","mouseout":"hideToolTip","dblclick":false,"rclick":false,"draggable":false,"proc":"bikesuche","cabfixflex":"flex","firmen":"500,510,530,540","objectname":"bikemarker","meta_id":"","standort_id":"16119","bikes":"8234","bikelist":[{"Number":"8234","Version":"5","canBeRented":true,"canBeReturned":false,"MarkeID":"1312","MarkeName":"CallBike","isPedelec":false,"FirmaID":"500"}],"objecttyp":"cab_standort","clustername":"bikecluster","filter":["cab_flex"]}},{"lat":"48.142582000000000","lng":"11.553828000000000","iconName":"bikeicon","iconNameSelected":"","hal2option":{"minZoom":"11","maxZoom":false,"tooltip":"'Arnulfstr.&nbsp;\/&nbsp;Hopfenstr.'","id":"23584552399906","openinfo":"openDynamicInfoWindow","click":"openDynamicInfoWindow","mouseover":"showToolTip","mouseout":"hideToolTip","dblclick":false,"rclick":false,"draggable":false,"proc":"bikesuche","cabfixflex":"flex","firmen":"500,510,530,540","objectname":"bikemarker","meta_id":"","standort_id":"46535","bikes":"6474","bikelist":[{"Number":"6474","Version":"5","canBeRented":true,"canBeReturned":false,"MarkeID":"1312","MarkeName":"CallBike","isPedelec":false,"FirmaID":"500"}],"objecttyp":"cab_standort","clustername":"bikecluster","filter":["cab_flex"]}},{"lat":"48.151666670000000","lng":"11.562500000000000","iconName":"bikeicon","iconNameSelected":"","hal2option":{"minZoom":"11","maxZoom":false,"tooltip":"'Schwindstr.&nbsp;\/&nbsp;Theresienstr.'","id":"23595627685482","openinfo":"openDynamicInfoWindow","click":"openDynamicInfoWindow","mouseover":"showToolTip","mouseout":"hideToolTip","dblclick":false,"rclick":false,"draggable":false,"proc":"bikesuche","cabfixflex":"flex","firmen":"500,510,530,540","objectname":"bikemarker","meta_id":"","standort_id":"39994","bikes":"0691","bikelist":[{"Number":"0691","Version":"5","canBeRented":true,"canBeReturned":false,"MarkeID":"1312","MarkeName":"CallBike","isPedelec":false,"FirmaID":"500"}],"objecttyp":"cab_standort","clustername":"bikecluster","filter":["cab_flex"]}},{"lat":"48.142456000000000","lng":"11.554017000000000","iconName":"bikeicon","iconNameSelected":"","hal2option":{"minZoom":"11","maxZoom":false,"tooltip":"'Arnulfstr.&nbsp;\/&nbsp;Hopfenstr.'","id":"23584714436383","openinfo":"openDynamicInfoWindow","click":"openDynamicInfoWindow","mouseover":"showToolTip","mouseout":"hideToolTip","dblclick":false,"rclick":false,"draggable":false,"proc":"bikesuche","cabfixflex":"flex","firmen":"500,510,530,540","objectname":"bikemarker","meta_id":"","standort_id":"46535","bikes":"6972","bikelist":[{"Number":"6972","Version":"5","canBeRented":true,"canBeReturned":false,"MarkeID":"1312","MarkeName":"CallBike","isPedelec":false,"FirmaID":"500"}],"objecttyp":"cab_standort","clustername":"bikecluster","filter":["cab_flex"]}},{"lat":"48.154350000000000","lng":"11.559482000000000","iconName":"bikeicon","iconNameSelected":"","hal2option":{"minZoom":"11","maxZoom":false,"tooltip":"'He\u00dfstr.&nbsp;\/&nbsp;Winzererstr.'","id":"23593205421195","openinfo":"openDynamicInfoWindow","click":"openDynamicInfoWindow","mouseover":"showToolTip","mouseout":"hideToolTip","dblclick":false,"rclick":false,"draggable":false,"proc":"bikesuche","cabfixflex":"flex","firmen":"500,510,530,540","objectname":"bikemarker","meta_id":"","standort_id":"16119","bikes":"0574","bikelist":[{"Number":"0574","Version":"5","canBeRented":true,"canBeReturned":false,"MarkeID":"1312","MarkeName":"CallBike","isPedelec":false,"FirmaID":"500"}],"objecttyp":"cab_standort","clustername":"bikecluster","filter":["cab_flex"]}},{"lat":"48.144554000000000","lng":"11.546253000000000","iconName":"bikeicon","iconNameSelected":"","hal2option":{"minZoom":"11","maxZoom":false,"tooltip":"'Arnulfstr.&nbsp;\/&nbsp;Deroystr.'","id":"23577302667103","openinfo":"openDynamicInfoWindow","click":"openDynamicInfoWindow","mouseover":"showToolTip","mouseout":"hideToolTip","dblclick":false,"rclick":false,"draggable":false,"proc":"bikesuche","cabfixflex":"flex","firmen":"500,510,530,540","objectname":"bikemarker","meta_id":"","standort_id":"40225","bikes":"0829","bikelist":[{"Number":"0829","Version":"5","canBeRented":true,"canBeReturned":false,"MarkeID":"1312","MarkeName":"CallBike","isPedelec":false,"FirmaID":"500"}],"objecttyp":"cab_standort","clustername":"bikecluster","filter":["cab_flex"]}},{"lat":"48.154408000000000","lng":"11.559607500000000","iconName":"bikeicon","iconNameSelected":"","hal2option":{"minZoom":"11","maxZoom":false,"tooltip":"'He\u00dfstr.&nbsp;\/&nbsp;Winzererstr.'","id":"23593347703852","openinfo":"openDynamicInfoWindow","click":"openDynamicInfoWindow","mouseover":"showToolTip","mouseout":"hideToolTip","dblclick":false,"rclick":false,"draggable":false,"proc":"bikesuche","cabfixflex":"flex","firmen":"500,510,530,540","objectname":"bikemarker","meta_id":"","standort_id":"16119","bikes":"2773","bikelist":[{"Number":"2773","Version":"5","canBeRented":true,"canBeReturned":false,"MarkeID":"1312","MarkeName":"CallBike","isPedelec":false,"FirmaID":"500"}],"objecttyp":"cab_standort","clustername":"bikecluster","filter":["cab_flex"]}},{"lat":"48.142223000000000","lng":"11.552397000000000","iconName":"bikeicon","iconNameSelected":"","hal2option":{"minZoom":"11","maxZoom":false,"tooltip":"'Arnulfstr.&nbsp;\/&nbsp;Herbststr.'","id":"23583003891755","openinfo":"openDynamicInfoWindow","click":"openDynamicInfoWindow","mouseover":"showToolTip","mouseout":"hideToolTip","dblclick":false,"rclick":false,"draggable":false,"proc":"bikesuche","cabfixflex":"flex","firmen":"500,510,530,540","objectname":"bikemarker","meta_id":"","standort_id":"16108","bikes":"0632","bikelist":[{"Number":"0632","Version":"5","canBeRented":true,"canBeReturned":false,"MarkeID":"1312","MarkeName":"CallBike","isPedelec":false,"FirmaID":"500"}],"objecttyp":"cab_standort","clustername":"bikecluster","filter":["cab_flex"]}},{"lat":"48.149260000000000","lng":"11.542889000000000","iconName":"bikeicon","iconNameSelected":"","hal2option":{"minZoom":"11","maxZoom":false,"tooltip":"'Blutenburgstr.&nbsp;\/&nbsp;Elvirastr.'","id":"2357501990693","openinfo":"openDynamicInfoWindow","click":"openDynamicInfoWindow","mouseover":"showToolTip","mouseout":"hideToolTip","dblclick":false,"rclick":false,"draggable":false,"proc":"bikesuche","cabfixflex":"flex","firmen":"500,510,530,540","objectname":"bikemarker","meta_id":"","standort_id":"34090","bikes":"1973","bikelist":[{"Number":"1973","Version":"5","canBeRented":true,"canBeReturned":false,"MarkeID":"1312","MarkeName":"CallBike","isPedelec":false,"FirmaID":"500"}],"objecttyp":"cab_standort","clustername":"bikecluster","filter":["cab_flex"]}},{"lat":"48.154533000000000","lng":"11.560573000000000","iconName":"bikeicon","iconNameSelected":"","hal2option":{"minZoom":"11","maxZoom":false,"tooltip":"'Schellingstr.&nbsp;\/&nbsp;Schlei\u00dfheimer&nbsp;Str.'","id":"23594363607171","openinfo":"openDynamicInfoWindow","click":"openDynamicInfoWindow","mouseover":"showToolTip","mouseout":"hideToolTip","dblclick":false,"rclick":false,"draggable":false,"proc":"bikesuche","cabfixflex":"flex","firmen":"500,510,530,540","objectname":"bikemarker","meta_id":"","standort_id":"14156","bikes":"0557","bikelist":[{"Number":"0557","Version":"5","canBeRented":true,"canBeReturned":false,"MarkeID":"1312","MarkeName":"CallBike","isPedelec":false,"FirmaID":"500"}],"objecttyp":"cab_standort","clustername":"bikecluster","filter":["cab_flex"]}},{"lat":"48.146557000000000","lng":"11.563785000000000","iconName":"bikeicon","iconNameSelected":"","hal2option":{"minZoom":"11","maxZoom":false,"tooltip":"'K\u00f6nigsplatz&nbsp;\/&nbsp;Luisenstr.'","id":"23595686759199","openinfo":"openDynamicInfoWindow","click":"openDynamicInfoWindow","mouseover":"showToolTip","mouseout":"hideToolTip","dblclick":false,"rclick":false,"draggable":false,"proc":"bikesuche","cabfixflex":"flex","firmen":"500,510,530,540","objectname":"bikemarker","meta_id":"","standort_id":"49060","bikes":"0284","bikelist":[{"Number":"0284","Version":"5","canBeRented":true,"canBeReturned":false,"MarkeID":"1312","MarkeName":"CallBike","isPedelec":false,"FirmaID":"500"}],"objecttyp":"cab_standort","clustername":"bikecluster","filter":["cab_flex"]}},{"lat":"48.150555560000000","lng":"11.543055560000000","iconName":"bikeicon","iconNameSelected":"","hal2option":{"minZoom":"11","maxZoom":false,"tooltip":"'Elvirastr.&nbsp;\/&nbsp;Nymphenburger&nbsp;Str.'","id":"23575507164724","openinfo":"openDynamicInfoWindow","click":"openDynamicInfoWindow","mouseover":"showToolTip","mouseout":"hideToolTip","dblclick":false,"rclick":false,"draggable":false,"proc":"bikesuche","cabfixflex":"flex","firmen":"500,510,530,540","objectname":"bikemarker","meta_id":"","standort_id":"253","bikes":"0009","bikelist":[{"Number":"0009","Version":"5","canBeRented":true,"canBeReturned":false,"MarkeID":"1312","MarkeName":"CallBike","isPedelec":false,"FirmaID":"500"}],"objecttyp":"cab_standort","clustername":"bikecluster","filter":["cab_flex"]}},{"lat":"48.146526000000000","lng":"11.563813000000000","iconName":"bikeicon","iconNameSelected":"","hal2option":{"minZoom":"11","maxZoom":false,"tooltip":"'K\u00f6nigsplatz&nbsp;\/&nbsp;Luisenstr.'","id":"23595707729662","openinfo":"openDynamicInfoWindow","click":"openDynamicInfoWindow","mouseover":"showToolTip","mouseout":"hideToolTip","dblclick":false,"rclick":false,"draggable":false,"proc":"bikesuche","cabfixflex":"flex","firmen":"500,510,530,540","objectname":"bikemarker","meta_id":"","standort_id":"49060","bikes":"1688","bikelist":[{"Number":"1688","Version":"5","canBeRented":true,"canBeReturned":false,"MarkeID":"1312","MarkeName":"CallBike","isPedelec":false,"FirmaID":"500"}],"objecttyp":"cab_standort","clustername":"bikecluster","filter":["cab_flex"]}},{"lat":"48.149260000000000","lng":"11.542780000000000","iconName":"bikeicon","iconNameSelected":"","hal2option":{"minZoom":"11","maxZoom":false,"tooltip":"'Blutenburgstr.&nbsp;\/&nbsp;Elvirastr.'","id":"23574908596701","openinfo":"openDynamicInfoWindow","click":"openDynamicInfoWindow","mouseover":"showToolTip","mouseout":"hideToolTip","dblclick":false,"rclick":false,"draggable":false,"proc":"bikesuche","cabfixflex":"flex","firmen":"500,510,530,540","objectname":"bikemarker","meta_id":"","standort_id":"34090","bikes":"6413","bikelist":[{"Number":"6413","Version":"5","canBeRented":true,"canBeReturned":false,"MarkeID":"1312","MarkeName":"CallBike","isPedelec":false,"FirmaID":"500"}],"objecttyp":"cab_standort","clustername":"bikecluster","filter":["cab_flex"]}},{"lat":"48.142696000000000","lng":"11.548291000000000","iconName":"bikeicon","iconNameSelected":"","hal2option":{"minZoom":"11","maxZoom":false,"tooltip":"'Arnulfstr.&nbsp;\/&nbsp;Hackerbr\u00fccke'","id":"23578928366924","openinfo":"openDynamicInfoWindow","click":"openDynamicInfoWindow","mouseover":"showToolTip","mouseout":"hideToolTip","dblclick":false,"rclick":false,"draggable":false,"proc":"bikesuche","cabfixflex":"flex","firmen":"500,510,530,540","objectname":"bikemarker","meta_id":"","standort_id":"43657","bikes":"2210","bikelist":[{"Number":"2210","Version":"5","canBeRented":true,"canBeReturned":false,"MarkeID":"1312","MarkeName":"CallBike","isPedelec":false,"FirmaID":"500"}],"objecttyp":"cab_standort","clustername":"bikecluster","filter":["cab_flex"]}},{"lat":"48.150670000000000","lng":"11.542900000000000","iconName":"bikeicon","iconNameSelected":"","hal2option":{"minZoom":"11","maxZoom":false,"tooltip":"'Elvirastr.&nbsp;\/&nbsp;Nymphenburger&nbsp;Str.'","id":"23575376322405","openinfo":"openDynamicInfoWindow","click":"openDynamicInfoWindow","mouseover":"showToolTip","mouseout":"hideToolTip","dblclick":false,"rclick":false,"draggable":false,"proc":"bikesuche","cabfixflex":"flex","firmen":"500,510,530,540","objectname":"bikemarker","meta_id":"","standort_id":"253","bikes":"0147","bikelist":[{"Number":"0147","Version":"5","canBeRented":true,"canBeReturned":false,"MarkeID":"1312","MarkeName":"CallBike","isPedelec":false,"FirmaID":"500"}],"objecttyp":"cab_standort","clustername":"bikecluster","filter":["cab_flex"]}},{"lat":"48.144630000000000","lng":"11.562509000000000","iconName":"bikeicon","iconNameSelected":"","hal2option":{"minZoom":"11","maxZoom":false,"tooltip":"'Karlstr.&nbsp;\/&nbsp;Luisenstr.'","id":"23593912725037","openinfo":"openDynamicInfoWindow","click":"openDynamicInfoWindow","mouseover":"showToolTip","mouseout":"hideToolTip","dblclick":false,"rclick":false,"draggable":false,"proc":"bikesuche","cabfixflex":"flex","firmen":"500,510,530,540","objectname":"bikemarker","meta_id":"","standort_id":"33984","bikes":"6513","bikelist":[{"Number":"6513","Version":"5","canBeRented":true,"canBeReturned":false,"MarkeID":"1312","MarkeName":"CallBike","isPedelec":false,"FirmaID":"500"}],"objecttyp":"cab_standort","clustername":"bikecluster","filter":["cab_flex"]}},{"lat":"48.147080000000000","lng":"11.564621000000000","iconName":"bikeicon","iconNameSelected":"","hal2option":{"minZoom":"11","maxZoom":false,"tooltip":"'K\u00f6nigsplatz&nbsp;\/&nbsp;Luisenstr.'","id":"23596667825282","openinfo":"openDynamicInfoWindow","click":"openDynamicInfoWindow","mouseover":"showToolTip","mouseout":"hideToolTip","dblclick":false,"rclick":false,"draggable":false,"proc":"bikesuche","cabfixflex":"flex","firmen":"500,510,530,540","objectname":"bikemarker","meta_id":"","standort_id":"49060","bikes":"7260","bikelist":[{"Number":"7260","Version":"5","canBeRented":true,"canBeReturned":false,"MarkeID":"1312","MarkeName":"CallBike","isPedelec":false,"FirmaID":"500"}],"objecttyp":"cab_standort","clustername":"bikecluster","filter":["cab_flex"]}},{"lat":"48.154102000000000","lng":"11.562462000000000","iconName":"bikeicon","iconNameSelected":"","hal2option":{"minZoom":"11","maxZoom":false,"tooltip":"'Schellingstr.&nbsp;\/&nbsp;Zentnerstr.'","id":"23596185592572","openinfo":"openDynamicInfoWindow","click":"openDynamicInfoWindow","mouseover":"showToolTip","mouseout":"hideToolTip","dblclick":false,"rclick":false,"draggable":false,"proc":"bikesuche","cabfixflex":"flex","firmen":"500,510,530,540","objectname":"bikemarker","meta_id":"","standort_id":"427","bikes":"3660","bikelist":[{"Number":"3660","Version":"5","canBeRented":true,"canBeReturned":false,"MarkeID":"1312","MarkeName":"CallBike","isPedelec":false,"FirmaID":"500"}],"objecttyp":"cab_standort","clustername":"bikecluster","filter":["cab_flex"]}},{"lat":"48.141705000000000","lng":"11.557736000000000","iconName":"bikeicon","iconNameSelected":"","hal2option":{"minZoom":"11","maxZoom":false,"tooltip":"'Hirtenstr.'","id":"23588325862169","openinfo":"openDynamicInfoWindow","click":"openDynamicInfoWindow","mouseover":"showToolTip","mouseout":"hideToolTip","dblclick":false,"rclick":false,"draggable":false,"proc":"bikesuche","cabfixflex":"flex","firmen":"500,510,530,540","objectname":"bikemarker","meta_id":"","standort_id":"34185","bikes":"5730","bikelist":[{"Number":"5730","Version":"5","canBeRented":true,"canBeReturned":false,"MarkeID":"1312","MarkeName":"CallBike","isPedelec":false,"FirmaID":"500"}],"objecttyp":"cab_standort","clustername":"bikecluster","filter":["cab_flex"]}},{"lat":"48.144142000000000","lng":"11.562823000000000","iconName":"bikeicon","iconNameSelected":"","hal2option":{"minZoom":"11","maxZoom":false,"tooltip":"'Karlstr.&nbsp;\/&nbsp;Luisenstr.'","id":"23594113512333","openinfo":"openDynamicInfoWindow","click":"openDynamicInfoWindow","mouseover":"showToolTip","mouseout":"hideToolTip","dblclick":false,"rclick":false,"draggable":false,"proc":"bikesuche","cabfixflex":"flex","firmen":"500,510,530,540","objectname":"bikemarker","meta_id":"","standort_id":"33984","bikes":"0867","bikelist":[{"Number":"0867","Version":"5","canBeRented":true,"canBeReturned":false,"MarkeID":"1312","MarkeName":"CallBike","isPedelec":false,"FirmaID":"500"}],"objecttyp":"cab_standort","clustername":"bikecluster","filter":["cab_flex"]}},{"lat":"48.149582000000000","lng":"11.541270000000000","iconName":"bikeicon","iconNameSelected":"","hal2option":{"minZoom":"11","maxZoom":false,"tooltip":"'Birkerstr.&nbsp;\/&nbsp;Blutenburgstr.'","id":"23573445362296","openinfo":"openDynamicInfoWindow","click":"openDynamicInfoWindow","mouseover":"showToolTip","mouseout":"hideToolTip","dblclick":false,"rclick":false,"draggable":false,"proc":"bikesuche","cabfixflex":"flex","firmen":"500,510,530,540","objectname":"bikemarker","meta_id":"","standort_id":"14122","bikes":"2041","bikelist":[{"Number":"2041","Version":"5","canBeRented":true,"canBeReturned":false,"MarkeID":"1312","MarkeName":"CallBike","isPedelec":false,"FirmaID":"500"}],"objecttyp":"cab_standort","clustername":"bikecluster","filter":["cab_flex"]}},{"lat":"48.141006000000000","lng":"11.550240000000000","iconName":"bikeicon","iconNameSelected":"","hal2option":{"minZoom":"11","maxZoom":false,"tooltip":"'Hackerbr\u00fccke&nbsp;\/&nbsp;S-Bahnstation&nbsp;Hackerbr\u00fccke'","id":"23580504090062","openinfo":"openDynamicInfoWindow","click":"openDynamicInfoWindow","mouseover":"showToolTip","mouseout":"hideToolTip","dblclick":false,"rclick":false,"draggable":false,"proc":"bikesuche","cabfixflex":"flex","firmen":"500,510,530,540","objectname":"bikemarker","meta_id":"","standort_id":"54538","bikes":"5220","bikelist":[{"Number":"5220","Version":"5","canBeRented":true,"canBeReturned":false,"MarkeID":"1312","MarkeName":"CallBike","isPedelec":false,"FirmaID":"500"}],"objecttyp":"cab_standort","clustername":"bikecluster","filter":["cab_flex"]}},{"lat":"48.142560000000000","lng":"11.561844000000000","iconName":"bikeicon","iconNameSelected":"","hal2option":{"minZoom":"11","maxZoom":false,"tooltip":"'Luisenstr.&nbsp;\/&nbsp;Sophienstr.'","id":"23592727025095","openinfo":"openDynamicInfoWindow","click":"openDynamicInfoWindow","mouseover":"showToolTip","mouseout":"hideToolTip","dblclick":false,"rclick":false,"draggable":false,"proc":"bikesuche","cabfixflex":"flex","firmen":"500,510,530,540","objectname":"bikemarker","meta_id":"","standort_id":"285","bikes":"0820","bikelist":[{"Number":"0820","Version":"5","canBeRented":true,"canBeReturned":false,"MarkeID":"1312","MarkeName":"CallBike","isPedelec":false,"FirmaID":"500"}],"objecttyp":"cab_standort","clustername":"bikecluster","filter":["cab_flex"]}},{"lat":"48.148487000000000","lng":"11.540829000000000","iconName":"bikeicon","iconNameSelected":"","hal2option":{"minZoom":"11","maxZoom":false,"tooltip":"'Birkerstr.&nbsp;\/&nbsp;Rupprechtstr.'","id":"23572726933381","openinfo":"openDynamicInfoWindow","click":"openDynamicInfoWindow","mouseover":"showToolTip","mouseout":"hideToolTip","dblclick":false,"rclick":false,"draggable":false,"proc":"bikesuche","cabfixflex":"flex","firmen":"500,510,530,540","objectname":"bikemarker","meta_id":"","standort_id":"33958","bikes":"0540","bikelist":[{"Number":"0540","Version":"5","canBeRented":true,"canBeReturned":false,"MarkeID":"1312","MarkeName":"CallBike","isPedelec":false,"FirmaID":"500"}],"objecttyp":"cab_standort","clustername":"bikecluster","filter":["cab_flex"]}},{"lat":"48.153187000000000","lng":"11.542399000000000","iconName":"bikeicon","iconNameSelected":"","hal2option":{"minZoom":"11","maxZoom":false,"tooltip":"'Albrechtstr.&nbsp;\/&nbsp;Kapschstr.'","id":"2357548085354","openinfo":"openDynamicInfoWindow","click":"openDynamicInfoWindow","mouseover":"showToolTip","mouseout":"hideToolTip","dblclick":false,"rclick":false,"draggable":false,"proc":"bikesuche","cabfixflex":"flex","firmen":"500,510,530,540","objectname":"bikemarker","meta_id":"","standort_id":"421","bikes":"1220","bikelist":[{"Number":"1220","Version":"5","canBeRented":true,"canBeReturned":false,"MarkeID":"1312","MarkeName":"CallBike","isPedelec":false,"FirmaID":"500"}],"objecttyp":"cab_standort","clustername":"bikecluster","filter":["cab_flex"]}},{"lat":"48.150810000000000","lng":"11.566249000000000","iconName":"bikeicon","iconNameSelected":"","hal2option":{"minZoom":"11","maxZoom":false,"tooltip":"'Enhuberstr.&nbsp;\/&nbsp;Theresienstr.'","id":"23599242742336","openinfo":"openDynamicInfoWindow","click":"openDynamicInfoWindow","mouseover":"showToolTip","mouseout":"hideToolTip","dblclick":false,"rclick":false,"draggable":false,"proc":"bikesuche","cabfixflex":"flex","firmen":"500,510,530,540","objectname":"bikemarker","meta_id":"","standort_id":"54406","bikes":"5219","bikelist":[{"Number":"5219","Version":"5","canBeRented":true,"canBeReturned":false,"MarkeID":"1312","MarkeName":"CallBike","isPedelec":false,"FirmaID":"500"}],"objecttyp":"cab_standort","clustername":"bikecluster","filter":["cab_flex"]}},{"lat":"48.149982000000000","lng":"11.540810000000000","iconName":"bikeicon","iconNameSelected":"","hal2option":{"minZoom":"11","maxZoom":false,"tooltip":"'Birkerstr.&nbsp;\/&nbsp;Blutenburgstr.'","id":"2357307349001","openinfo":"openDynamicInfoWindow","click":"openDynamicInfoWindow","mouseover":"showToolTip","mouseout":"hideToolTip","dblclick":false,"rclick":false,"draggable":false,"proc":"bikesuche","cabfixflex":"flex","firmen":"500,510,530,540","objectname":"bikemarker","meta_id":"","standort_id":"14122","bikes":"5882","bikelist":[{"Number":"5882","Version":"5","canBeRented":true,"canBeReturned":false,"MarkeID":"1312","MarkeName":"CallBike","isPedelec":false,"FirmaID":"500"}],"objecttyp":"cab_standort","clustername":"bikecluster","filter":["cab_flex"]}},{"lat":"48.149880000000000","lng":"11.540630000000000","iconName":"bikeicon","iconNameSelected":"","hal2option":{"minZoom":"11","maxZoom":false,"tooltip":"'Blutenburgstr.&nbsp;\/&nbsp;Gabrielenstr.'","id":"23572864688544","openinfo":"openDynamicInfoWindow","click":"openDynamicInfoWindow","mouseover":"showToolTip","mouseout":"hideToolTip","dblclick":false,"rclick":false,"draggable":false,"proc":"bikesuche","cabfixflex":"flex","firmen":"500,510,530,540","objectname":"bikemarker","meta_id":"","standort_id":"420","bikes":"4302","bikelist":[{"Number":"4302","Version":"5","canBeRented":true,"canBeReturned":false,"MarkeID":"1312","MarkeName":"CallBike","isPedelec":false,"FirmaID":"500"}],"objecttyp":"cab_standort","clustername":"bikecluster","filter":["cab_flex"]}},{"lat":"48.149790000000000","lng":"11.566695000000000","iconName":"bikeicon","iconNameSelected":"","hal2option":{"minZoom":"11","maxZoom":false,"tooltip":"'Luisenstr.&nbsp;\/&nbsp;Theresienstr.'","id":"23599447774133","openinfo":"openDynamicInfoWindow","click":"openDynamicInfoWindow","mouseover":"showToolTip","mouseout":"hideToolTip","dblclick":false,"rclick":false,"draggable":false,"proc":"bikesuche","cabfixflex":"flex","firmen":"500,510,530,540","objectname":"bikemarker","meta_id":"","standort_id":"33991","bikes":"1916","bikelist":[{"Number":"1916","Version":"5","canBeRented":true,"canBeReturned":false,"MarkeID":"1312","MarkeName":"CallBike","isPedelec":false,"FirmaID":"500"}],"objecttyp":"cab_standort","clustername":"bikecluster","filter":["cab_flex"]}},{"lat":"48.156111110000000","lng":"11.561944440000000","iconName":"bikeicon","iconNameSelected":"","hal2option":{"minZoom":"11","maxZoom":false,"tooltip":"'G\u00f6rresstr.&nbsp;\/&nbsp;Schlei\u00dfheimer&nbsp;Str.'","id":"23596149709228","openinfo":"openDynamicInfoWindow","click":"openDynamicInfoWindow","mouseover":"showToolTip","mouseout":"hideToolTip","dblclick":false,"rclick":false,"draggable":false,"proc":"bikesuche","cabfixflex":"flex","firmen":"500,510,530,540","objectname":"bikemarker","meta_id":"","standort_id":"33982","bikes":"8099","bikelist":[{"Number":"8099","Version":"5","canBeRented":true,"canBeReturned":false,"MarkeID":"1312","MarkeName":"CallBike","isPedelec":false,"FirmaID":"500"}],"objecttyp":"cab_standort","clustername":"bikecluster","filter":["cab_flex"]}},{"lat":"48.152960000000000","lng":"11.541250000000000","iconName":"bikeicon","iconNameSelected":"","hal2option":{"minZoom":"11","maxZoom":false,"tooltip":"'Hedwigstr.&nbsp;\/&nbsp;Jutastr.'","id":"23574251835424","openinfo":"openDynamicInfoWindow","click":"openDynamicInfoWindow","mouseover":"showToolTip","mouseout":"hideToolTip","dblclick":false,"rclick":false,"draggable":false,"proc":"bikesuche","cabfixflex":"flex","firmen":"500,510,530,540","objectname":"bikemarker","meta_id":"","standort_id":"16078","bikes":"1452","bikelist":[{"Number":"1452","Version":"5","canBeRented":true,"canBeReturned":false,"MarkeID":"1312","MarkeName":"CallBike","isPedelec":false,"FirmaID":"500"}],"objecttyp":"cab_standort","clustername":"bikecluster","filter":["cab_flex"]}},{"lat":"48.141197000000000","lng":"11.560790000000000","iconName":"bikeicon","iconNameSelected":"","hal2option":{"minZoom":"11","maxZoom":false,"tooltip":"'Arnulfstr.&nbsp;\/&nbsp;Dachauer&nbsp;Str.'","id":"23591317658529","openinfo":"openDynamicInfoWindow","click":"openDynamicInfoWindow","mouseover":"showToolTip","mouseout":"hideToolTip","dblclick":false,"rclick":false,"draggable":false,"proc":"bikesuche","cabfixflex":"flex","firmen":"500,510,530,540","objectname":"bikemarker","meta_id":"","standort_id":"16121","bikes":"6307","bikelist":[{"Number":"6307","Version":"5","canBeRented":true,"canBeReturned":false,"MarkeID":"1312","MarkeName":"CallBike","isPedelec":false,"FirmaID":"500"}],"objecttyp":"cab_standort","clustername":"bikecluster","filter":["cab_flex"]}},{"lat":"48.152905000000000","lng":"11.541073000000000","iconName":"bikeicon","iconNameSelected":"","hal2option":{"minZoom":"11","maxZoom":false,"tooltip":"'Hedwigstr.&nbsp;\/&nbsp;Jutastr.'","id":"23574057600826","openinfo":"openDynamicInfoWindow","click":"openDynamicInfoWindow","mouseover":"showToolTip","mouseout":"hideToolTip","dblclick":false,"rclick":false,"draggable":false,"proc":"bikesuche","cabfixflex":"flex","firmen":"500,510,530,540","objectname":"bikemarker","meta_id":"","standort_id":"16078","bikes":"5952","bikelist":[{"Number":"5952","Version":"5","canBeRented":true,"canBeReturned":false,"MarkeID":"1312","MarkeName":"CallBike","isPedelec":false,"FirmaID":"500"}],"objecttyp":"cab_standort","clustername":"bikecluster","filter":["cab_flex"]}},{"lat":"48.157413000000000","lng":"11.547789000000000","iconName":"bikeicon","iconNameSelected":"","hal2option":{"minZoom":"11","maxZoom":false,"tooltip":"'Hilblestr.&nbsp;\/&nbsp;Pf\u00e4nderstr.'","id":"23582019508724","openinfo":"openDynamicInfoWindow","click":"openDynamicInfoWindow","mouseover":"showToolTip","mouseout":"hideToolTip","dblclick":false,"rclick":false,"draggable":false,"proc":"bikesuche","cabfixflex":"flex","firmen":"500,510,530,540","objectname":"bikemarker","meta_id":"","standort_id":"8856","bikes":"0386","bikelist":[{"Number":"0386","Version":"5","canBeRented":true,"canBeReturned":false,"MarkeID":"1312","MarkeName":"CallBike","isPedelec":false,"FirmaID":"500"}],"objecttyp":"cab_standort","clustername":"bikecluster","filter":["cab_flex"]}},{"lat":"48.151333000000000","lng":"11.540087000000000","iconName":"bikeicon","iconNameSelected":"","hal2option":{"minZoom":"11","maxZoom":false,"tooltip":"'Hedwigstr.&nbsp;\/&nbsp;Nymphenburger&nbsp;Str.'","id":"2357266578022","openinfo":"openDynamicInfoWindow","click":"openDynamicInfoWindow","mouseover":"showToolTip","mouseout":"hideToolTip","dblclick":false,"rclick":false,"draggable":false,"proc":"bikesuche","cabfixflex":"flex","firmen":"500,510,530,540","objectname":"bikemarker","meta_id":"","standort_id":"14116","bikes":"1592","bikelist":[{"Number":"1592","Version":"5","canBeRented":true,"canBeReturned":false,"MarkeID":"1312","MarkeName":"CallBike","isPedelec":false,"FirmaID":"500"}],"objecttyp":"cab_standort","clustername":"bikecluster","filter":["cab_flex"]}},{"lat":"48.142933000000000","lng":"11.542940000000000","iconName":"bikeicon","iconNameSelected":"","hal2option":{"minZoom":"11","maxZoom":false,"tooltip":"'Bike-Standort'","id":"23573523008728","openinfo":"openDynamicInfoWindow","click":"openDynamicInfoWindow","mouseover":"showToolTip","mouseout":"hideToolTip","dblclick":false,"rclick":false,"draggable":false,"proc":"bikesuche","cabfixflex":"flex","firmen":"500,510,530,540","objectname":"bikemarker","meta_id":"","standort_id":"","bikes":"0291","bikelist":[{"Number":"0291","Version":"5","canBeRented":true,"canBeReturned":false,"MarkeID":"1312","MarkeName":"CallBike","isPedelec":false,"FirmaID":"500"}],"objecttyp":"cab_standort","clustername":"bikecluster","filter":["cab_flex"]}},{"lat":"48.153100000000000","lng":"11.566470000000000","iconName":"bikeicon","iconNameSelected":"","hal2option":{"minZoom":"11","maxZoom":false,"tooltip":"'Augustenstr.&nbsp;\/&nbsp;Schellingstr.'","id":"23600029376189","openinfo":"openDynamicInfoWindow","click":"openDynamicInfoWindow","mouseover":"showToolTip","mouseout":"hideToolTip","dblclick":false,"rclick":false,"draggable":false,"proc":"bikesuche","cabfixflex":"flex","firmen":"500,510,530,540","objectname":"bikemarker","meta_id":"","standort_id":"8898","bikes":"7393","bikelist":[{"Number":"7393","Version":"5","canBeRented":true,"canBeReturned":false,"MarkeID":"1312","MarkeName":"CallBike","isPedelec":false,"FirmaID":"500"}],"objecttyp":"cab_standort","clustername":"bikecluster","filter":["cab_flex"]}},{"lat":"48.145382000000000","lng":"11.540503500000000","iconName":"bikeicon","iconNameSelected":"","hal2option":{"minZoom":"11","maxZoom":false,"tooltip":"'Arnulfstr.&nbsp;\/&nbsp;Marsstr.'","id":"23571634425297","openinfo":"openDynamicInfoWindow","click":"openDynamicInfoWindow","mouseover":"showToolTip","mouseout":"hideToolTip","dblclick":false,"rclick":false,"draggable":false,"proc":"bikesuche","cabfixflex":"flex","firmen":"500,510,530,540","objectname":"bikemarker","meta_id":"","standort_id":"34094","bikes":"0234","bikelist":[{"Number":"0234","Version":"5","canBeRented":true,"canBeReturned":false,"MarkeID":"1312","MarkeName":"CallBike","isPedelec":false,"FirmaID":"500"}],"objecttyp":"cab_standort","clustername":"bikecluster","filter":["cab_flex"]}},{"lat":"48.153534000000000","lng":"11.541092000000000","iconName":"bikeicon","iconNameSelected":"","hal2option":{"minZoom":"11","maxZoom":false,"tooltip":"'Albrechtstr.&nbsp;\/&nbsp;Hedwigstr.'","id":"23574230974077","openinfo":"openDynamicInfoWindow","click":"openDynamicInfoWindow","mouseover":"showToolTip","mouseout":"hideToolTip","dblclick":false,"rclick":false,"draggable":false,"proc":"bikesuche","cabfixflex":"flex","firmen":"500,510,530,540","objectname":"bikemarker","meta_id":"","standort_id":"9005","bikes":"0811","bikelist":[{"Number":"0811","Version":"5","canBeRented":true,"canBeReturned":false,"MarkeID":"1312","MarkeName":"CallBike","isPedelec":false,"FirmaID":"500"}],"objecttyp":"cab_standort","clustername":"bikecluster","filter":["cab_flex"]}},{"lat":"48.153183000000000","lng":"11.540748000000000","iconName":"bikeicon","iconNameSelected":"","hal2option":{"minZoom":"11","maxZoom":false,"tooltip":"'Hedwigstr.&nbsp;\/&nbsp;Jutastr.'","id":"23573793721013","openinfo":"openDynamicInfoWindow","click":"openDynamicInfoWindow","mouseover":"showToolTip","mouseout":"hideToolTip","dblclick":false,"rclick":false,"draggable":false,"proc":"bikesuche","cabfixflex":"flex","firmen":"500,510,530,540","objectname":"bikemarker","meta_id":"","standort_id":"16078","bikes":"1238","bikelist":[{"Number":"1238","Version":"5","canBeRented":true,"canBeReturned":false,"MarkeID":"1312","MarkeName":"CallBike","isPedelec":false,"FirmaID":"500"}],"objecttyp":"cab_standort","clustername":"bikecluster","filter":["cab_flex"]}},{"lat":"48.141167000000000","lng":"11.545485500000000","iconName":"bikeicon","iconNameSelected":"","hal2option":{"minZoom":"11","maxZoom":false,"tooltip":"'Arnulfstr.&nbsp;\/&nbsp;Deroystr.'","id":"23575689715289","openinfo":"openDynamicInfoWindow","click":"openDynamicInfoWindow","mouseover":"showToolTip","mouseout":"hideToolTip","dblclick":false,"rclick":false,"draggable":false,"proc":"bikesuche","cabfixflex":"flex","firmen":"500,510,530,540","objectname":"bikemarker","meta_id":"","standort_id":"40225","bikes":"5226","bikelist":[{"Number":"5226","Version":"5","canBeRented":true,"canBeReturned":false,"MarkeID":"1312","MarkeName":"CallBike","isPedelec":false,"FirmaID":"500"}],"objecttyp":"cab_standort","clustername":"bikecluster","filter":["cab_flex"]}},{"lat":"48.146873000000000","lng":"11.567656500000000","iconName":"bikeicon","iconNameSelected":"","hal2option":{"minZoom":"11","maxZoom":false,"tooltip":"'Arcisstr.&nbsp;\/&nbsp;Gabelsbergerstr.'","id":"2359971373583","openinfo":"openDynamicInfoWindow","click":"openDynamicInfoWindow","mouseover":"showToolTip","mouseout":"hideToolTip","dblclick":false,"rclick":false,"draggable":false,"proc":"bikesuche","cabfixflex":"flex","firmen":"500,510,530,540","objectname":"bikemarker","meta_id":"","standort_id":"14170","bikes":"1349","bikelist":[{"Number":"1349","Version":"5","canBeRented":true,"canBeReturned":false,"MarkeID":"1312","MarkeName":"CallBike","isPedelec":false,"FirmaID":"500"}],"objecttyp":"cab_standort","clustername":"bikecluster","filter":["cab_flex"]}},{"lat":"48.146700000000000","lng":"11.567608000000000","iconName":"bikeicon","iconNameSelected":"","hal2option":{"minZoom":"11","maxZoom":false,"tooltip":"'Arcisstr.&nbsp;\/&nbsp;Gabelsbergerstr.'","id":"2359962186336","openinfo":"openDynamicInfoWindow","click":"openDynamicInfoWindow","mouseover":"showToolTip","mouseout":"hideToolTip","dblclick":false,"rclick":false,"draggable":false,"proc":"bikesuche","cabfixflex":"flex","firmen":"500,510,530,540","objectname":"bikemarker","meta_id":"","standort_id":"14170","bikes":"0247","bikelist":[{"Number":"0247","Version":"5","canBeRented":true,"canBeReturned":false,"MarkeID":"1312","MarkeName":"CallBike","isPedelec":false,"FirmaID":"500"}],"objecttyp":"cab_standort","clustername":"bikecluster","filter":["cab_flex"]}},{"lat":"48.147500000000000","lng":"11.568055560000000","iconName":"bikeicon","iconNameSelected":"","hal2option":{"minZoom":"11","maxZoom":false,"tooltip":"'Arcisstr.&nbsp;\/&nbsp;Gabelsbergerstr.'","id":"23600274470334","openinfo":"openDynamicInfoWindow","click":"openDynamicInfoWindow","mouseover":"showToolTip","mouseout":"hideToolTip","dblclick":false,"rclick":false,"draggable":false,"proc":"bikesuche","cabfixflex":"flex","firmen":"500,510,530,540","objectname":"bikemarker","meta_id":"","standort_id":"14170","bikes":"0040","bikelist":[{"Number":"0040","Version":"5","canBeRented":true,"canBeReturned":false,"MarkeID":"1312","MarkeName":"CallBike","isPedelec":false,"FirmaID":"500"}],"objecttyp":"cab_standort","clustername":"bikecluster","filter":["cab_flex"]}},{"lat":"48.152820000000000","lng":"11.567151000000000","iconName":"bikeicon","iconNameSelected":"","hal2option":{"minZoom":"11","maxZoom":false,"tooltip":"'Luisenstr.&nbsp;\/&nbsp;Schellingstr.'","id":"23600655499706","openinfo":"openDynamicInfoWindow","click":"openDynamicInfoWindow","mouseover":"showToolTip","mouseout":"hideToolTip","dblclick":false,"rclick":false,"draggable":false,"proc":"bikesuche","cabfixflex":"flex","firmen":"500,510,530,540","objectname":"bikemarker","meta_id":"","standort_id":"16141","bikes":"1564","bikelist":[{"Number":"1564","Version":"5","canBeRented":true,"canBeReturned":false,"MarkeID":"1312","MarkeName":"CallBike","isPedelec":false,"FirmaID":"500"}],"objecttyp":"cab_standort","clustername":"bikecluster","filter":["cab_flex"]}},{"lat":"48.157658000000000","lng":"11.561192000000000","iconName":"bikeicon","iconNameSelected":"","hal2option":{"minZoom":"11","maxZoom":false,"tooltip":"'Georgenstr.&nbsp;\/&nbsp;Winzererstr.'","id":"23595760856737","openinfo":"openDynamicInfoWindow","click":"openDynamicInfoWindow","mouseover":"showToolTip","mouseout":"hideToolTip","dblclick":false,"rclick":false,"draggable":false,"proc":"bikesuche","cabfixflex":"flex","firmen":"500,510,530,540","objectname":"bikemarker","meta_id":"","standort_id":"46547","bikes":"2155","bikelist":[{"Number":"2155","Version":"5","canBeRented":true,"canBeReturned":false,"MarkeID":"1312","MarkeName":"CallBike","isPedelec":false,"FirmaID":"500"}],"objecttyp":"cab_standort","clustername":"bikecluster","filter":["cab_flex"]}},{"lat":"48.149050000000000","lng":"11.568649000000000","iconName":"bikeicon","iconNameSelected":"","hal2option":{"minZoom":"11","maxZoom":false,"tooltip":"'Arcisstr.21TU-M\u00fcnchen&nbsp;Hauptgeb\u00e4ude'","id":"23601259693784","openinfo":"openDynamicInfoWindow","click":"openDynamicInfoWindow","mouseover":"showToolTip","mouseout":"hideToolTip","dblclick":false,"rclick":false,"draggable":false,"proc":"bikesuche","cabfixflex":"flex","firmen":"500,510,530,540","objectname":"bikemarker","meta_id":"","standort_id":"50787","bikes":"0635","bikelist":[{"Number":"0635","Version":"5","canBeRented":true,"canBeReturned":false,"MarkeID":"1312","MarkeName":"CallBike","isPedelec":false,"FirmaID":"500"}],"objecttyp":"cab_standort","clustername":"bikecluster","filter":["cab_flex"]}},{"lat":"48.139248000000000","lng":"11.557628000000000","iconName":"bikeicon","iconNameSelected":"","hal2option":{"minZoom":"11","maxZoom":false,"tooltip":"'Bayerstr.&nbsp;\/&nbsp;Mittererstr.'","id":"23587613711093","openinfo":"openDynamicInfoWindow","click":"openDynamicInfoWindow","mouseover":"showToolTip","mouseout":"hideToolTip","dblclick":false,"rclick":false,"draggable":false,"proc":"bikesuche","cabfixflex":"flex","firmen":"500,510,530,540","objectname":"bikemarker","meta_id":"","standort_id":"274","bikes":"1657","bikelist":[{"Number":"1657","Version":"5","canBeRented":true,"canBeReturned":false,"MarkeID":"1312","MarkeName":"CallBike","isPedelec":false,"FirmaID":"500"}],"objecttyp":"cab_standort","clustername":"bikecluster","filter":["cab_flex"]}},{"lat":"48.157578000000000","lng":"11.562079000000000","iconName":"bikeicon","iconNameSelected":"","hal2option":{"minZoom":"11","maxZoom":false,"tooltip":"'Keuslinstr.&nbsp;\/&nbsp;Schlei\u00dfheimer&nbsp;Str.'","id":"23596646399111","openinfo":"openDynamicInfoWindow","click":"openDynamicInfoWindow","mouseover":"showToolTip","mouseout":"hideToolTip","dblclick":false,"rclick":false,"draggable":false,"proc":"bikesuche","cabfixflex":"flex","firmen":"500,510,530,540","objectname":"bikemarker","meta_id":"","standort_id":"9096","bikes":"3870","bikelist":[{"Number":"3870","Version":"5","canBeRented":true,"canBeReturned":false,"MarkeID":"1312","MarkeName":"CallBike","isPedelec":false,"FirmaID":"500"}],"objecttyp":"cab_standort","clustername":"bikecluster","filter":["cab_flex"]}},{"lat":"48.157475000000000","lng":"11.544425000000000","iconName":"bikeicon","iconNameSelected":"","hal2option":{"minZoom":"11","maxZoom":false,"tooltip":"'Fasaneriestr.&nbsp;\/&nbsp;Leonrodstr.'","id":"23578599583666","openinfo":"openDynamicInfoWindow","click":"openDynamicInfoWindow","mouseover":"showToolTip","mouseout":"hideToolTip","dblclick":false,"rclick":false,"draggable":false,"proc":"bikesuche","cabfixflex":"flex","firmen":"500,510,530,540","objectname":"bikemarker","meta_id":"","standort_id":"16085","bikes":"1577","bikelist":[{"Number":"1577","Version":"5","canBeRented":true,"canBeReturned":false,"MarkeID":"1312","MarkeName":"CallBike","isPedelec":false,"FirmaID":"500"}],"objecttyp":"cab_standort","clustername":"bikecluster","filter":["cab_flex"]}},{"lat":"48.152374000000000","lng":"11.538362000000000","iconName":"bikeicon","iconNameSelected":"","hal2option":{"minZoom":"11","maxZoom":false,"tooltip":"'Horemansstr.&nbsp;\/&nbsp;Olgastr.'","id":"23571158698108","openinfo":"openDynamicInfoWindow","click":"openDynamicInfoWindow","mouseover":"showToolTip","mouseout":"hideToolTip","dblclick":false,"rclick":false,"draggable":false,"proc":"bikesuche","cabfixflex":"flex","firmen":"500,510,530,540","objectname":"bikemarker","meta_id":"","standort_id":"40116","bikes":"0926","bikelist":[{"Number":"0926","Version":"5","canBeRented":true,"canBeReturned":false,"MarkeID":"1312","MarkeName":"CallBike","isPedelec":false,"FirmaID":"500"}],"objecttyp":"cab_standort","clustername":"bikecluster","filter":["cab_flex"]}},{"lat":"48.152187000000000","lng":"11.569009000000000","iconName":"bikeicon","iconNameSelected":"","hal2option":{"minZoom":"11","maxZoom":false,"tooltip":"'Luisenstr.&nbsp;\/&nbsp;Schellingstr.'","id":"23602395742227","openinfo":"openDynamicInfoWindow","click":"openDynamicInfoWindow","mouseover":"showToolTip","mouseout":"hideToolTip","dblclick":false,"rclick":false,"draggable":false,"proc":"bikesuche","cabfixflex":"flex","firmen":"500,510,530,540","objectname":"bikemarker","meta_id":"","standort_id":"16141","bikes":"1358","bikelist":[{"Number":"1358","Version":"5","canBeRented":true,"canBeReturned":false,"MarkeID":"1312","MarkeName":"CallBike","isPedelec":false,"FirmaID":"500"}],"objecttyp":"cab_standort","clustername":"bikecluster","filter":["cab_flex"]}},{"lat":"48.152447000000000","lng":"11.568895000000000","iconName":"bikeicon","iconNameSelected":"","hal2option":{"minZoom":"11","maxZoom":false,"tooltip":"'Luisenstr.&nbsp;\/&nbsp;Schellingstr.'","id":"23602343174695","openinfo":"openDynamicInfoWindow","click":"openDynamicInfoWindow","mouseover":"showToolTip","mouseout":"hideToolTip","dblclick":false,"rclick":false,"draggable":false,"proc":"bikesuche","cabfixflex":"flex","firmen":"500,510,530,540","objectname":"bikemarker","meta_id":"","standort_id":"16141","bikes":"0878","bikelist":[{"Number":"0878","Version":"5","canBeRented":true,"canBeReturned":false,"MarkeID":"1312","MarkeName":"CallBike","isPedelec":false,"FirmaID":"500"}],"objecttyp":"cab_standort","clustername":"bikecluster","filter":["cab_flex"]}},{"lat":"48.159607000000000","lng":"11.557236000000000","iconName":"bikeicon","iconNameSelected":"","hal2option":{"minZoom":"11","maxZoom":false,"tooltip":"'Kathi-Kobus-Str.&nbsp;\/&nbsp;Theo-Prosel-Weg'","id":"23592200909755","openinfo":"openDynamicInfoWindow","click":"openDynamicInfoWindow","mouseover":"showToolTip","mouseout":"hideToolTip","dblclick":false,"rclick":false,"draggable":false,"proc":"bikesuche","cabfixflex":"flex","firmen":"500,510,530,540","objectname":"bikemarker","meta_id":"","standort_id":"14361","bikes":"0643","bikelist":[{"Number":"0643","Version":"5","canBeRented":true,"canBeReturned":false,"MarkeID":"1312","MarkeName":"CallBike","isPedelec":false,"FirmaID":"500"}],"objecttyp":"cab_standort","clustername":"bikecluster","filter":["cab_flex"]}},{"lat":"48.159046000000000","lng":"11.560160000000000","iconName":"bikeicon","iconNameSelected":"","hal2option":{"minZoom":"11","maxZoom":false,"tooltip":"'Winzererstr.&nbsp;\/&nbsp;Wormser&nbsp;Str.'","id":"23595047726321","openinfo":"openDynamicInfoWindow","click":"openDynamicInfoWindow","mouseover":"showToolTip","mouseout":"hideToolTip","dblclick":false,"rclick":false,"draggable":false,"proc":"bikesuche","cabfixflex":"flex","firmen":"500,510,530,540","objectname":"bikemarker","meta_id":"","standort_id":"9095","bikes":"1682","bikelist":[{"Number":"1682","Version":"5","canBeRented":true,"canBeReturned":false,"MarkeID":"1312","MarkeName":"CallBike","isPedelec":false,"FirmaID":"500"}],"objecttyp":"cab_standort","clustername":"bikecluster","filter":["cab_flex"]}},{"lat":"48.148994000000000","lng":"11.537189000000000","iconName":"bikeicon","iconNameSelected":"","hal2option":{"minZoom":"11","maxZoom":false,"tooltip":"'Hirschbergstr.&nbsp;\/&nbsp;Landshuter&nbsp;Allee'","id":"23569133287795","openinfo":"openDynamicInfoWindow","click":"openDynamicInfoWindow","mouseover":"showToolTip","mouseout":"hideToolTip","dblclick":false,"rclick":false,"draggable":false,"proc":"bikesuche","cabfixflex":"flex","firmen":"500,510,530,540","objectname":"bikemarker","meta_id":"","standort_id":"22714","bikes":"0404","bikelist":[{"Number":"0404","Version":"5","canBeRented":true,"canBeReturned":false,"MarkeID":"1312","MarkeName":"CallBike","isPedelec":false,"FirmaID":"500"}],"objecttyp":"cab_standort","clustername":"bikecluster","filter":["cab_flex"]}},{"lat":"48.146828000000000","lng":"11.569768000000000","iconName":"bikeicon","iconNameSelected":"","hal2option":{"minZoom":"11","maxZoom":false,"tooltip":"'Barer&nbsp;Str.&nbsp;\/&nbsp;Gabelsbergerstr.'","id":"23601856492571","openinfo":"openDynamicInfoWindow","click":"openDynamicInfoWindow","mouseover":"showToolTip","mouseout":"hideToolTip","dblclick":false,"rclick":false,"draggable":false,"proc":"bikesuche","cabfixflex":"flex","firmen":"500,510,530,540","objectname":"bikemarker","meta_id":"","standort_id":"40018","bikes":"0656","bikelist":[{"Number":"0656","Version":"5","canBeRented":true,"canBeReturned":false,"MarkeID":"1312","MarkeName":"CallBike","isPedelec":false,"FirmaID":"500"}],"objecttyp":"cab_standort","clustername":"bikecluster","filter":["cab_flex"]}},{"lat":"48.146637000000000","lng":"11.569740000000000","iconName":"bikeicon","iconNameSelected":"","hal2option":{"minZoom":"11","maxZoom":false,"tooltip":"'Barer&nbsp;Str.&nbsp;\/&nbsp;Gabelsbergerstr.'","id":"23601781118475","openinfo":"openDynamicInfoWindow","click":"openDynamicInfoWindow","mouseover":"showToolTip","mouseout":"hideToolTip","dblclick":false,"rclick":false,"draggable":false,"proc":"bikesuche","cabfixflex":"flex","firmen":"500,510,530,540","objectname":"bikemarker","meta_id":"","standort_id":"40018","bikes":"2282","bikelist":[{"Number":"2282","Version":"5","canBeRented":true,"canBeReturned":false,"MarkeID":"1312","MarkeName":"CallBike","isPedelec":false,"FirmaID":"500"}],"objecttyp":"cab_standort","clustername":"bikecluster","filter":["cab_flex"]}},{"lat":"48.150833330000000","lng":"11.570000000000000","iconName":"bikeicon","iconNameSelected":"","hal2option":{"minZoom":"11","maxZoom":false,"tooltip":"'Arcisstr.&nbsp;\/&nbsp;He\u00dfstr.'","id":"23603074834184","openinfo":"openDynamicInfoWindow","click":"openDynamicInfoWindow","mouseover":"showToolTip","mouseout":"hideToolTip","dblclick":false,"rclick":false,"draggable":false,"proc":"bikesuche","cabfixflex":"flex","firmen":"500,510,530,540","objectname":"bikemarker","meta_id":"","standort_id":"14370","bikes":"1108","bikelist":[{"Number":"1108","Version":"5","canBeRented":true,"canBeReturned":false,"MarkeID":"1312","MarkeName":"CallBike","isPedelec":false,"FirmaID":"500"}],"objecttyp":"cab_standort","clustername":"bikecluster","filter":["cab_flex"]}},{"lat":"48.139160000000000","lng":"11.546083000000000","iconName":"bikeicon","iconNameSelected":"","hal2option":{"minZoom":"11","maxZoom":false,"tooltip":"'Holzapfelstr.&nbsp;\/&nbsp;Landsberger&nbsp;Str.'","id":"23575808298132","openinfo":"openDynamicInfoWindow","click":"openDynamicInfoWindow","mouseover":"showToolTip","mouseout":"hideToolTip","dblclick":false,"rclick":false,"draggable":false,"proc":"bikesuche","cabfixflex":"flex","firmen":"500,510,530,540","objectname":"bikemarker","meta_id":"","standort_id":"16092","bikes":"1012","bikelist":[{"Number":"1012","Version":"5","canBeRented":true,"canBeReturned":false,"MarkeID":"1312","MarkeName":"CallBike","isPedelec":false,"FirmaID":"500"}],"objecttyp":"cab_standort","clustername":"bikecluster","filter":["cab_flex"]}},{"lat":"48.151880000000000","lng":"11.537428000000000","iconName":"bikeicon","iconNameSelected":"","hal2option":{"minZoom":"11","maxZoom":false,"tooltip":"'Landshuter&nbsp;Allee\/Mittlerer&nbsp;Ring&nbsp;\/&nbsp;Nymphenburger&nbsp;Str.'","id":"23570083762359","openinfo":"openDynamicInfoWindow","click":"openDynamicInfoWindow","mouseover":"showToolTip","mouseout":"hideToolTip","dblclick":false,"rclick":false,"draggable":false,"proc":"bikesuche","cabfixflex":"flex","firmen":"500,510,530,540","objectname":"bikemarker","meta_id":"","standort_id":"8845","bikes":"2252","bikelist":[{"Number":"2252","Version":"5","canBeRented":true,"canBeReturned":false,"MarkeID":"1312","MarkeName":"CallBike","isPedelec":false,"FirmaID":"500"}],"objecttyp":"cab_standort","clustername":"bikecluster","filter":["cab_flex"]}},{"lat":"48.158546000000000","lng":"11.562468000000000","iconName":"bikeicon","iconNameSelected":"","hal2option":{"minZoom":"11","maxZoom":false,"tooltip":"'Agnesstr.&nbsp;\/&nbsp;Schlei\u00dfheimer&nbsp;Str.'","id":"23597280501183","openinfo":"openDynamicInfoWindow","click":"openDynamicInfoWindow","mouseover":"showToolTip","mouseout":"hideToolTip","dblclick":false,"rclick":false,"draggable":false,"proc":"bikesuche","cabfixflex":"flex","firmen":"500,510,530,540","objectname":"bikemarker","meta_id":"","standort_id":"8889","bikes":"1325","bikelist":[{"Number":"1325","Version":"5","canBeRented":true,"canBeReturned":false,"MarkeID":"1312","MarkeName":"CallBike","isPedelec":false,"FirmaID":"500"}],"objecttyp":"cab_standort","clustername":"bikecluster","filter":["cab_flex"]}},{"lat":"48.146664000000000","lng":"11.570187000000000","iconName":"bikeicon","iconNameSelected":"","hal2option":{"minZoom":"11","maxZoom":false,"tooltip":"'Barer&nbsp;Str.&nbsp;\/&nbsp;Gabelsbergerstr.'","id":"23602243662545","openinfo":"openDynamicInfoWindow","click":"openDynamicInfoWindow","mouseover":"showToolTip","mouseout":"hideToolTip","dblclick":false,"rclick":false,"draggable":false,"proc":"bikesuche","cabfixflex":"flex","firmen":"500,510,530,540","objectname":"bikemarker","meta_id":"","standort_id":"40018","bikes":"1180","bikelist":[{"Number":"1180","Version":"5","canBeRented":true,"canBeReturned":false,"MarkeID":"1312","MarkeName":"CallBike","isPedelec":false,"FirmaID":"500"}],"objecttyp":"cab_standort","clustername":"bikecluster","filter":["cab_flex"]}},{"lat":"48.142777780000000","lng":"11.567777780000000","iconName":"bikeicon","iconNameSelected":"","hal2option":{"minZoom":"11","maxZoom":false,"tooltip":"'Barer&nbsp;Str.&nbsp;\/&nbsp;Karlstr.'","id":"23598833765061","openinfo":"openDynamicInfoWindow","click":"openDynamicInfoWindow","mouseover":"showToolTip","mouseout":"hideToolTip","dblclick":false,"rclick":false,"draggable":false,"proc":"bikesuche","cabfixflex":"flex","firmen":"500,510,530,540","objectname":"bikemarker","meta_id":"","standort_id":"22882","bikes":"0559","bikelist":[{"Number":"0559","Version":"5","canBeRented":true,"canBeReturned":false,"MarkeID":"1312","MarkeName":"CallBike","isPedelec":false,"FirmaID":"500"}],"objecttyp":"cab_standort","clustername":"bikecluster","filter":["cab_flex"]}},{"lat":"48.137802000000000","lng":"11.550920000000000","iconName":"bikeicon","iconNameSelected":"","hal2option":{"minZoom":"11","maxZoom":false,"tooltip":"'Martin-Greif-Str.&nbsp;\/&nbsp;Schwanthalerstr.'","id":"2358041347979","openinfo":"openDynamicInfoWindow","click":"openDynamicInfoWindow","mouseover":"showToolTip","mouseout":"hideToolTip","dblclick":false,"rclick":false,"draggable":false,"proc":"bikesuche","cabfixflex":"flex","firmen":"500,510,530,540","objectname":"bikemarker","meta_id":"","standort_id":"29339","bikes":"0520","bikelist":[{"Number":"0520","Version":"5","canBeRented":true,"canBeReturned":false,"MarkeID":"1312","MarkeName":"CallBike","isPedelec":false,"FirmaID":"500"}],"objecttyp":"cab_standort","clustername":"bikecluster","filter":["cab_flex"]}},{"lat":"48.158016000000000","lng":"11.564397000000000","iconName":"bikeicon","iconNameSelected":"","hal2option":{"minZoom":"11","maxZoom":false,"tooltip":"'Agnesstr.&nbsp;\/&nbsp;Zentnerstr.'","id":"23599118961443","openinfo":"openDynamicInfoWindow","click":"openDynamicInfoWindow","mouseover":"showToolTip","mouseout":"hideToolTip","dblclick":false,"rclick":false,"draggable":false,"proc":"bikesuche","cabfixflex":"flex","firmen":"500,510,530,540","objectname":"bikemarker","meta_id":"","standort_id":"16128","bikes":"5218","bikelist":[{"Number":"5218","Version":"5","canBeRented":true,"canBeReturned":false,"MarkeID":"1312","MarkeName":"CallBike","isPedelec":false,"FirmaID":"500"}],"objecttyp":"cab_standort","clustername":"bikecluster","filter":["cab_flex"]}},{"lat":"48.150764000000000","lng":"11.570852000000000","iconName":"bikeicon","iconNameSelected":"","hal2option":{"minZoom":"11","maxZoom":false,"tooltip":"'He\u00dfstr.&nbsp;\/&nbsp;Schraudolphstr.'","id":"23603926875224","openinfo":"openDynamicInfoWindow","click":"openDynamicInfoWindow","mouseover":"showToolTip","mouseout":"hideToolTip","dblclick":false,"rclick":false,"draggable":false,"proc":"bikesuche","cabfixflex":"flex","firmen":"500,510,530,540","objectname":"bikemarker","meta_id":"","standort_id":"33998","bikes":"8164","bikelist":[{"Number":"8164","Version":"5","canBeRented":true,"canBeReturned":false,"MarkeID":"1312","MarkeName":"CallBike","isPedelec":false,"FirmaID":"500"}],"objecttyp":"cab_standort","clustername":"bikecluster","filter":["cab_flex"]}},{"lat":"48.160683000000000","lng":"11.552447000000000","iconName":"bikeicon","iconNameSelected":"","hal2option":{"minZoom":"11","maxZoom":false,"tooltip":"'Infanteriestr.'","id":"23587575921262","openinfo":"openDynamicInfoWindow","click":"openDynamicInfoWindow","mouseover":"showToolTip","mouseout":"hideToolTip","dblclick":false,"rclick":false,"draggable":false,"proc":"bikesuche","cabfixflex":"flex","firmen":"500,510,530,540","objectname":"bikemarker","meta_id":"","standort_id":"9092","bikes":"1505","bikelist":[{"Number":"1505","Version":"5","canBeRented":true,"canBeReturned":false,"MarkeID":"1312","MarkeName":"CallBike","isPedelec":false,"FirmaID":"500"}],"objecttyp":"cab_standort","clustername":"bikecluster","filter":["cab_flex"]}},{"lat":"48.137360000000000","lng":"11.550373000000000","iconName":"bikeicon","iconNameSelected":"","hal2option":{"minZoom":"11","maxZoom":false,"tooltip":"'Martin-Greif-Str.&nbsp;\/&nbsp;Schwanthalerstr.'","id":"23579746886582","openinfo":"openDynamicInfoWindow","click":"openDynamicInfoWindow","mouseover":"showToolTip","mouseout":"hideToolTip","dblclick":false,"rclick":false,"draggable":false,"proc":"bikesuche","cabfixflex":"flex","firmen":"500,510,530,540","objectname":"bikemarker","meta_id":"","standort_id":"29339","bikes":"0064","bikelist":[{"Number":"0064","Version":"5","canBeRented":true,"canBeReturned":false,"MarkeID":"1312","MarkeName":"CallBike","isPedelec":false,"FirmaID":"500"}],"objecttyp":"cab_standort","clustername":"bikecluster","filter":["cab_flex"]}},{"lat":"48.157380000000000","lng":"11.566296000000000","iconName":"bikeicon","iconNameSelected":"","hal2option":{"minZoom":"11","maxZoom":false,"tooltip":"'Hiltenspergerstr.&nbsp;\/&nbsp;Keuslinstr.'","id":"23600900653672","openinfo":"openDynamicInfoWindow","click":"openDynamicInfoWindow","mouseover":"showToolTip","mouseout":"hideToolTip","dblclick":false,"rclick":false,"draggable":false,"proc":"bikesuche","cabfixflex":"flex","firmen":"500,510,530,540","objectname":"bikemarker","meta_id":"","standort_id":"16131","bikes":"6998","bikelist":[{"Number":"6998","Version":"5","canBeRented":true,"canBeReturned":false,"MarkeID":"1312","MarkeName":"CallBike","isPedelec":false,"FirmaID":"500"}],"objecttyp":"cab_standort","clustername":"bikecluster","filter":["cab_flex"]}},{"lat":"48.140263000000000","lng":"11.565806000000000","iconName":"bikeicon","iconNameSelected":"","hal2option":{"minZoom":"11","maxZoom":false,"tooltip":"'Elisenstr.&nbsp;\/&nbsp;Karlsplatz'","id":"23596206107063","openinfo":"openDynamicInfoWindow","click":"openDynamicInfoWindow","mouseover":"showToolTip","mouseout":"hideToolTip","dblclick":false,"rclick":false,"draggable":false,"proc":"bikesuche","cabfixflex":"flex","firmen":"500,510,530,540","objectname":"bikemarker","meta_id":"","standort_id":"291","bikes":"0842","bikelist":[{"Number":"0842","Version":"5","canBeRented":true,"canBeReturned":false,"MarkeID":"1312","MarkeName":"CallBike","isPedelec":false,"FirmaID":"500"}],"objecttyp":"cab_standort","clustername":"bikecluster","filter":["cab_flex"]}},{"lat":"48.157150000000000","lng":"11.567080000000000","iconName":"bikeicon","iconNameSelected":"","hal2option":{"minZoom":"11","maxZoom":false,"tooltip":"'Adelheidstr.&nbsp;\/&nbsp;Georgenstr.'","id":"23601644150821","openinfo":"openDynamicInfoWindow","click":"openDynamicInfoWindow","mouseover":"showToolTip","mouseout":"hideToolTip","dblclick":false,"rclick":false,"draggable":false,"proc":"bikesuche","cabfixflex":"flex","firmen":"500,510,530,540","objectname":"bikemarker","meta_id":"","standort_id":"299","bikes":"1410","bikelist":[{"Number":"1410","Version":"5","canBeRented":true,"canBeReturned":false,"MarkeID":"1312","MarkeName":"CallBike","isPedelec":false,"FirmaID":"500"}],"objecttyp":"cab_standort","clustername":"bikecluster","filter":["cab_flex"]}},{"lat":"48.150654000000000","lng":"11.571819000000000","iconName":"bikeicon","iconNameSelected":"","hal2option":{"minZoom":"11","maxZoom":false,"tooltip":"'He\u00dfstr.&nbsp;\/&nbsp;Schraudolphstr.'","id":"23604886206454","openinfo":"openDynamicInfoWindow","click":"openDynamicInfoWindow","mouseover":"showToolTip","mouseout":"hideToolTip","dblclick":false,"rclick":false,"draggable":false,"proc":"bikesuche","cabfixflex":"flex","firmen":"500,510,530,540","objectname":"bikemarker","meta_id":"","standort_id":"33998","bikes":"5870","bikelist":[{"Number":"5870","Version":"5","canBeRented":true,"canBeReturned":false,"MarkeID":"1312","MarkeName":"CallBike","isPedelec":false,"FirmaID":"500"}],"objecttyp":"cab_standort","clustername":"bikecluster","filter":["cab_flex"]}},{"lat":"48.160797000000000","lng":"11.559142000000000","iconName":"bikeicon","iconNameSelected":"","hal2option":{"minZoom":"11","maxZoom":false,"tooltip":"'BSC&nbsp;MUC&nbsp;\/&nbsp;Kathi-Kobus-Str.'","id":"23594437720704","openinfo":"openDynamicInfoWindow","click":"openDynamicInfoWindow","mouseover":"showToolTip","mouseout":"hideToolTip","dblclick":false,"rclick":false,"draggable":false,"proc":"bikesuche","cabfixflex":"flex","firmen":"500,510,530,540","objectname":"bikemarker","meta_id":"","standort_id":"9016","bikes":"2067","bikelist":[{"Number":"2067","Version":"5","canBeRented":true,"canBeReturned":false,"MarkeID":"1312","MarkeName":"CallBike","isPedelec":false,"FirmaID":"500"}],"objecttyp":"cab_standort","clustername":"bikecluster","filter":["cab_flex"]}},{"lat":"48.156593000000000","lng":"11.568324000000000","iconName":"bikeicon","iconNameSelected":"","hal2option":{"minZoom":"11","maxZoom":false,"tooltip":"'Georgenstr.&nbsp;\/&nbsp;Tengstr.'","id":"23602776755292","openinfo":"openDynamicInfoWindow","click":"openDynamicInfoWindow","mouseover":"showToolTip","mouseout":"hideToolTip","dblclick":false,"rclick":false,"draggable":false,"proc":"bikesuche","cabfixflex":"flex","firmen":"500,510,530,540","objectname":"bikemarker","meta_id":"","standort_id":"22777","bikes":"6593","bikelist":[{"Number":"6593","Version":"5","canBeRented":true,"canBeReturned":false,"MarkeID":"1312","MarkeName":"CallBike","isPedelec":false,"FirmaID":"500"}],"objecttyp":"cab_standort","clustername":"bikecluster","filter":["cab_flex"]}},{"lat":"48.157978000000000","lng":"11.566462000000000","iconName":"bikeicon","iconNameSelected":"","hal2option":{"minZoom":"11","maxZoom":false,"tooltip":"'Agnesstr.&nbsp;\/&nbsp;Hiltenspergerstr.'","id":"23601216547751","openinfo":"openDynamicInfoWindow","click":"openDynamicInfoWindow","mouseover":"showToolTip","mouseout":"hideToolTip","dblclick":false,"rclick":false,"draggable":false,"proc":"bikesuche","cabfixflex":"flex","firmen":"500,510,530,540","objectname":"bikemarker","meta_id":"","standort_id":"33989","bikes":"0986","bikelist":[{"Number":"0986","Version":"5","canBeRented":true,"canBeReturned":false,"MarkeID":"1312","MarkeName":"CallBike","isPedelec":false,"FirmaID":"500"}],"objecttyp":"cab_standort","clustername":"bikecluster","filter":["cab_flex"]}},{"lat":"48.161666670000000","lng":"11.553333330000000","iconName":"bikeicon","iconNameSelected":"","hal2option":{"minZoom":"11","maxZoom":false,"tooltip":"'Ackermannstr.&nbsp;\/&nbsp;Schwere-Reiter-Str.'","id":"23588721643338","openinfo":"openDynamicInfoWindow","click":"openDynamicInfoWindow","mouseover":"showToolTip","mouseout":"hideToolTip","dblclick":false,"rclick":false,"draggable":false,"proc":"bikesuche","cabfixflex":"flex","firmen":"500,510,530,540","objectname":"bikemarker","meta_id":"","standort_id":"503","bikes":"6982","bikelist":[{"Number":"6982","Version":"5","canBeRented":true,"canBeReturned":false,"MarkeID":"1312","MarkeName":"CallBike","isPedelec":false,"FirmaID":"500"}],"objecttyp":"cab_standort","clustername":"bikecluster","filter":["cab_flex"]}},{"lat":"48.155510000000000","lng":"11.570010000000000","iconName":"bikeicon","iconNameSelected":"","hal2option":{"minZoom":"11","maxZoom":false,"tooltip":"'Isabellastr.&nbsp;\/&nbsp;Neureutherstr.'","id":"23604231236266","openinfo":"openDynamicInfoWindow","click":"openDynamicInfoWindow","mouseover":"showToolTip","mouseout":"hideToolTip","dblclick":false,"rclick":false,"draggable":false,"proc":"bikesuche","cabfixflex":"flex","firmen":"500,510,530,540","objectname":"bikemarker","meta_id":"","standort_id":"22784","bikes":"0502","bikelist":[{"Number":"0502","Version":"5","canBeRented":true,"canBeReturned":false,"MarkeID":"1312","MarkeName":"CallBike","isPedelec":false,"FirmaID":"500"}],"objecttyp":"cab_standort","clustername":"bikecluster","filter":["cab_flex"]}},{"lat":"48.158752000000000","lng":"11.566277500000000","iconName":"bikeicon","iconNameSelected":"","hal2option":{"minZoom":"11","maxZoom":false,"tooltip":"'Hiltenspergerstr.&nbsp;\/&nbsp;Krumbacherstr.'","id":"23601217970386","openinfo":"openDynamicInfoWindow","click":"openDynamicInfoWindow","mouseover":"showToolTip","mouseout":"hideToolTip","dblclick":false,"rclick":false,"draggable":false,"proc":"bikesuche","cabfixflex":"flex","firmen":"500,510,530,540","objectname":"bikemarker","meta_id":"","standort_id":"506","bikes":"0229","bikelist":[{"Number":"0229","Version":"5","canBeRented":true,"canBeReturned":false,"MarkeID":"1312","MarkeName":"CallBike","isPedelec":false,"FirmaID":"500"}],"objecttyp":"cab_standort","clustername":"bikecluster","filter":["cab_flex"]}},{"lat":"48.160492000000000","lng":"11.544723000000000","iconName":"bikeicon","iconNameSelected":"","hal2option":{"minZoom":"11","maxZoom":false,"tooltip":"'Hartliebstr.&nbsp;\/&nbsp;Merianstr.'","id":"23579642484222","openinfo":"openDynamicInfoWindow","click":"openDynamicInfoWindow","mouseover":"showToolTip","mouseout":"hideToolTip","dblclick":false,"rclick":false,"draggable":false,"proc":"bikesuche","cabfixflex":"flex","firmen":"500,510,530,540","objectname":"bikemarker","meta_id":"","standort_id":"40119","bikes":"1214","bikelist":[{"Number":"1214","Version":"5","canBeRented":true,"canBeReturned":false,"MarkeID":"1312","MarkeName":"CallBike","isPedelec":false,"FirmaID":"500"}],"objecttyp":"cab_standort","clustername":"bikecluster","filter":["cab_flex"]}},{"lat":"48.159195000000000","lng":"11.541681000000000","iconName":"bikeicon","iconNameSelected":"","hal2option":{"minZoom":"11","maxZoom":false,"tooltip":"'Fasaneriestr.&nbsp;\/&nbsp;H\u00fcbnerstr.'","id":"23576218227417","openinfo":"openDynamicInfoWindow","click":"openDynamicInfoWindow","mouseover":"showToolTip","mouseout":"hideToolTip","dblclick":false,"rclick":false,"draggable":false,"proc":"bikesuche","cabfixflex":"flex","firmen":"500,510,530,540","objectname":"bikemarker","meta_id":"","standort_id":"423","bikes":"5915","bikelist":[{"Number":"5915","Version":"5","canBeRented":true,"canBeReturned":false,"MarkeID":"1312","MarkeName":"CallBike","isPedelec":false,"FirmaID":"500"}],"objecttyp":"cab_standort","clustername":"bikecluster","filter":["cab_flex"]}},{"lat":"48.156452000000000","lng":"11.537709000000000","iconName":"bikeicon","iconNameSelected":"","hal2option":{"minZoom":"11","maxZoom":false,"tooltip":"'Albrechtstr.&nbsp;\/&nbsp;Volkartstr.'","id":"23571489763027","openinfo":"openDynamicInfoWindow","click":"openDynamicInfoWindow","mouseover":"showToolTip","mouseout":"hideToolTip","dblclick":false,"rclick":false,"draggable":false,"proc":"bikesuche","cabfixflex":"flex","firmen":"500,510,530,540","objectname":"bikemarker","meta_id":"","standort_id":"245","bikes":"6677","bikelist":[{"Number":"6677","Version":"5","canBeRented":true,"canBeReturned":false,"MarkeID":"1312","MarkeName":"CallBike","isPedelec":false,"FirmaID":"500"}],"objecttyp":"cab_standort","clustername":"bikecluster","filter":["cab_flex"]}},{"lat":"48.149498000000000","lng":"11.573132500000000","iconName":"bikeicon","iconNameSelected":"","hal2option":{"minZoom":"11","maxZoom":false,"tooltip":"'Barer&nbsp;Str.&nbsp;\/&nbsp;He\u00dfstr.'","id":"23605942475624","openinfo":"openDynamicInfoWindow","click":"openDynamicInfoWindow","mouseover":"showToolTip","mouseout":"hideToolTip","dblclick":false,"rclick":false,"draggable":false,"proc":"bikesuche","cabfixflex":"flex","firmen":"500,510,5